xengine/__init__.py
xengine/art.py
xengine/version.py
xengine-0.0.1.dist-info/LICENSE
xengine-0.0.1.dist-info/METADATA
xengine-0.0.1.dist-info/WHEEL
xengine-0.0.1.dist-info/top_level.txt
xengine-0.0.1.dist-info/RECORD
